[
  {
    "id": "cot-001",
    "productSource": "증권",
    "questionType": "상품비교 추천형",
    "questioner": "user-0015",
    "products": [
      "product-042"
    ],
    "question": "30대 직장인으로 안정적인 투자를 원합니다. 어떤 상품을 추천하시나요?",
    "cot1": "먼저 고객의 현재 상황과 투자 목적을 파악해보겠습니다.",
    "cot2": "고객의 위험성향과 투자 기간을 고려하여 적합한 상품군을 선별합니다.",
    "cot3": "선별된 상품들의 특징과 장단점을 비교 분석합니다.",
    "answer": "고객의 상황에 맞는 최적의 상품을 추천드립니다.",
    "status": "검토중",
    "author": "관리자",
    "createdAt": "2025-08-23T15:11:33.074Z",
    "updatedAt": "2025-09-20T22:49:15.359Z"
  },
  {
    "id": "cot-002",
    "productSource": "보험",
    "questionType": "투자성 상품 추천형",
    "questioner": "user-0039",
    "products": [
      "product-023",
      "product-048",
      "product-028"
    ],
    "question": "40대 가장으로서 가족을 위한 보장보험을 찾고 있습니다.",
    "cot1": "먼저 고객의 현재 상황과 투자 목적을 파악해보겠습니다.",
    "cot2": "고객의 위험성향과 투자 기간을 고려하여 적합한 상품군을 선별합니다.",
    "cot3": "선별된 상품들의 특징과 장단점을 비교 분석합니다.",
    "answer": "고객의 상황에 맞는 최적의 상품을 추천드립니다.",
    "status": "완료",
    "author": "관리자",
    "createdAt": "2025-09-11T12:06:04.497Z",
    "updatedAt": "2025-09-20T22:49:15.359Z"
  },
  {
    "id": "cot-003",
    "productSource": "증권",
    "questionType": "투자성향 및 조건 기반형",
    "questioner": "user-0088",
    "products": [
      "product-039",
      "product-040",
      "product-039"
    ],
    "question": "은퇴 준비를 위한 장기 투자 상품을 찾고 있습니다.",
    "cot1": "먼저 고객의 현재 상황과 투자 목적을 파악해보겠습니다.",
    "cot2": "고객의 위험성향과 투자 기간을 고려하여 적합한 상품군을 선별합니다.",
    "cot3": "선별된 상품들의 특징과 장단점을 비교 분석합니다.",
    "answer": "고객의 상황에 맞는 최적의 상품을 추천드립니다.",
    "status": "보류",
    "author": "관리자",
    "createdAt": "2025-09-15T03:54:19.974Z",
    "updatedAt": "2025-09-20T22:49:15.359Z"
  },
  {
    "id": "cot-004",
    "productSource": "증권",
    "questionType": "투자성향 및 조건 기반형",
    "questioner": "user-0063",
    "products": [
      "product-037",
      "product-041"
    ],
    "question": "은퇴 준비를 위한 장기 투자 상품을 찾고 있습니다.",
    "cot1": "먼저 고객의 현재 상황과 투자 목적을 파악해보겠습니다.",
    "cot2": "고객의 위험성향과 투자 기간을 고려하여 적합한 상품군을 선별합니다.",
    "cot3": "선별된 상품들의 특징과 장단점을 비교 분석합니다.",
    "answer": "고객의 상황에 맞는 최적의 상품을 추천드립니다.",
    "status": "완료",
    "author": "관리자",
    "createdAt": "2025-09-18T11:54:23.698Z",
    "updatedAt": "2025-09-20T22:49:15.359Z"
  },
  {
    "id": "cot-005",
    "productSource": "증권",
    "questionType": "고객 특성 강조형",
    "questioner": "user-0011",
    "products": [
      "product-036"
    ],
    "question": "은퇴 준비를 위한 장기 투자 상품을 찾고 있습니다.",
    "cot1": "먼저 고객의 현재 상황과 투자 목적을 파악해보겠습니다.",
    "cot2": "고객의 위험성향과 투자 기간을 고려하여 적합한 상품군을 선별합니다.",
    "cot3": "선별된 상품들의 특징과 장단점을 비교 분석합니다.",
    "answer": "고객의 상황에 맞는 최적의 상품을 추천드립니다.",
    "status": "보류",
    "author": "관리자",
    "createdAt": "2025-09-03T08:19:24.821Z",
    "updatedAt": "2025-09-20T22:49:15.359Z"
  },
  {
    "id": "cot-006",
    "productSource": "보험",
    "questionType": "투자성 상품 추천형",
    "questioner": "user-0099",
    "products": [
      "product-035",
      "product-041",
      "product-014"
    ],
    "question": "노후 준비를 위한 연금보험 상품을 추천해주세요.",
    "cot1": "먼저 고객의 현재 상황과 투자 목적을 파악해보겠습니다.",
    "cot2": "고객의 위험성향과 투자 기간을 고려하여 적합한 상품군을 선별합니다.",
    "cot3": "선별된 상품들의 특징과 장단점을 비교 분석합니다.",
    "answer": "고객의 상황에 맞는 최적의 상품을 추천드립니다.",
    "status": "보류",
    "author": "관리자",
    "createdAt": "2025-08-27T19:14:36.308Z",
    "updatedAt": "2025-09-20T22:49:15.359Z"
  },
  {
    "id": "cot-007",
    "productSource": "증권",
    "questionType": "고객 특성 강조형",
    "questioner": "user-0016",
    "products": [
      "product-022",
      "product-016",
      "product-022"
    ],
    "question": "해외 투자에 관심이 있는데 초보자도 할 수 있는 상품이 있나요?",
    "cot1": "먼저 고객의 현재 상황과 투자 목적을 파악해보겠습니다.",
    "cot2": "고객의 위험성향과 투자 기간을 고려하여 적합한 상품군을 선별합니다.",
    "cot3": "선별된 상품들의 특징과 장단점을 비교 분석합니다.",
    "answer": "고객의 상황에 맞는 최적의 상품을 추천드립니다.",
    "status": "보류",
    "author": "관리자",
    "createdAt": "2025-09-01T09:47:51.353Z",
    "updatedAt": "2025-09-20T22:49:15.359Z"
  },
  {
    "id": "cot-008",
    "productSource": "증권",
    "questionType": "상품비교 추천형",
    "questioner": "user-0017",
    "products": [
      "product-004",
      "product-035"
    ],
    "question": "해외 투자에 관심이 있는데 초보자도 할 수 있는 상품이 있나요?",
    "cot1": "먼저 고객의 현재 상황과 투자 목적을 파악해보겠습니다.",
    "cot2": "고객의 위험성향과 투자 기간을 고려하여 적합한 상품군을 선별합니다.",
    "cot3": "선별된 상품들의 특징과 장단점을 비교 분석합니다.",
    "answer": "고객의 상황에 맞는 최적의 상품을 추천드립니다.",
    "status": "완료",
    "author": "관리자",
    "createdAt": "2025-09-19T11:42:43.937Z",
    "updatedAt": "2025-09-20T22:49:15.359Z"
  },
  {
    "id": "cot-009",
    "productSource": "보험",
    "questionType": "투자성 상품 추천형",
    "questioner": "user-0037",
    "products": [
      "product-003",
      "product-018",
      "product-021"
    ],
    "question": "건강에 대한 걱정이 많아 실손보험을 알아보고 있습니다.",
    "cot1": "먼저 고객의 현재 상황과 투자 목적을 파악해보겠습니다.",
    "cot2": "고객의 위험성향과 투자 기간을 고려하여 적합한 상품군을 선별합니다.",
    "cot3": "선별된 상품들의 특징과 장단점을 비교 분석합니다.",
    "answer": "고객의 상황에 맞는 최적의 상품을 추천드립니다.",
    "status": "보류",
    "author": "관리자",
    "createdAt": "2025-09-09T15:52:39.164Z",
    "updatedAt": "2025-09-20T22:49:15.359Z"
  },
  {
    "id": "cot-010",
    "productSource": "보험",
    "questionType": "투자성 상품 추천형",
    "questioner": "user-0074",
    "products": [
      "product-041",
      "product-026",
      "product-023"
    ],
    "question": "노후 준비를 위한 연금보험 상품을 추천해주세요.",
    "cot1": "먼저 고객의 현재 상황과 투자 목적을 파악해보겠습니다.",
    "cot2": "고객의 위험성향과 투자 기간을 고려하여 적합한 상품군을 선별합니다.",
    "cot3": "선별된 상품들의 특징과 장단점을 비교 분석합니다.",
    "answer": "고객의 상황에 맞는 최적의 상품을 추천드립니다.",
    "status": "검토중",
    "author": "관리자",
    "createdAt": "2025-08-25T07:55:39.659Z",
    "updatedAt": "2025-09-20T22:49:15.359Z"
  },
  {
    "id": "cot-011",
    "productSource": "증권",
    "questionType": "고객 특성 강조형",
    "questioner": "user-0016",
    "products": [
      "product-014",
      "product-009",
      "product-005"
    ],
    "question": "은퇴 준비를 위한 장기 투자 상품을 찾고 있습니다.",
    "cot1": "먼저 고객의 현재 상황과 투자 목적을 파악해보겠습니다.",
    "cot2": "고객의 위험성향과 투자 기간을 고려하여 적합한 상품군을 선별합니다.",
    "cot3": "선별된 상품들의 특징과 장단점을 비교 분석합니다.",
    "answer": "고객의 상황에 맞는 최적의 상품을 추천드립니다.",
    "status": "완료",
    "author": "관리자",
    "createdAt": "2025-09-07T02:41:27.455Z",
    "updatedAt": "2025-09-20T22:49:15.359Z"
  },
  {
    "id": "cot-012",
    "productSource": "증권",
    "questionType": "투자성향 및 조건 기반형",
    "questioner": "user-0071",
    "products": [
      "product-023",
      "product-005",
      "product-031"
    ],
    "question": "은퇴 준비를 위한 장기 투자 상품을 찾고 있습니다.",
    "cot1": "먼저 고객의 현재 상황과 투자 목적을 파악해보겠습니다.",
    "cot2": "고객의 위험성향과 투자 기간을 고려하여 적합한 상품군을 선별합니다.",
    "cot3": "선별된 상품들의 특징과 장단점을 비교 분석합니다.",
    "answer": "고객의 상황에 맞는 최적의 상품을 추천드립니다.",
    "status": "검토중",
    "author": "관리자",
    "createdAt": "2025-09-04T04:34:33.205Z",
    "updatedAt": "2025-09-20T22:49:15.359Z"
  },
  {
    "id": "cot-013",
    "productSource": "증권",
    "questionType": "투자성향 및 조건 기반형",
    "questioner": "user-0037",
    "products": [
      "product-006",
      "product-032"
    ],
    "question": "해외 투자에 관심이 있는데 초보자도 할 수 있는 상품이 있나요?",
    "cot1": "먼저 고객의 현재 상황과 투자 목적을 파악해보겠습니다.",
    "cot2": "고객의 위험성향과 투자 기간을 고려하여 적합한 상품군을 선별합니다.",
    "cot3": "선별된 상품들의 특징과 장단점을 비교 분석합니다.",
    "answer": "고객의 상황에 맞는 최적의 상품을 추천드립니다.",
    "status": "보류",
    "author": "관리자",
    "createdAt": "2025-09-20T18:17:55.237Z",
    "updatedAt": "2025-09-20T22:49:15.359Z"
  },
  {
    "id": "cot-014",
    "productSource": "보험",
    "questionType": "건강 및 질병 보장 대비형",
    "questioner": "user-0035",
    "products": [
      "product-041",
      "product-008",
      "product-022"
    ],
    "question": "건강에 대한 걱정이 많아 실손보험을 알아보고 있습니다.",
    "cot1": "먼저 고객의 현재 상황과 투자 목적을 파악해보겠습니다.",
    "cot2": "고객의 위험성향과 투자 기간을 고려하여 적합한 상품군을 선별합니다.",
    "cot3": "선별된 상품들의 특징과 장단점을 비교 분석합니다.",
    "answer": "고객의 상황에 맞는 최적의 상품을 추천드립니다.",
    "status": "검토중",
    "author": "관리자",
    "createdAt": "2025-09-10T00:56:16.109Z",
    "updatedAt": "2025-09-20T22:49:15.359Z"
  },
  {
    "id": "cot-015",
    "productSource": "보험",
    "questionType": "건강 및 질병 보장 대비형",
    "questioner": "user-0093",
    "products": [
      "product-001",
      "product-038"
    ],
    "question": "40대 가장으로서 가족을 위한 보장보험을 찾고 있습니다.",
    "cot1": "먼저 고객의 현재 상황과 투자 목적을 파악해보겠습니다.",
    "cot2": "고객의 위험성향과 투자 기간을 고려하여 적합한 상품군을 선별합니다.",
    "cot3": "선별된 상품들의 특징과 장단점을 비교 분석합니다.",
    "answer": "고객의 상황에 맞는 최적의 상품을 추천드립니다.",
    "status": "초안",
    "author": "관리자",
    "createdAt": "2025-09-10T14:14:38.686Z",
    "updatedAt": "2025-09-20T22:49:15.359Z"
  },
  {
    "id": "cot-016",
    "productSource": "증권",
    "questionType": "투자성향 및 조건 기반형",
    "questioner": "user-0063",
    "products": [
      "product-040",
      "product-029"
    ],
    "question": "30대 직장인으로 안정적인 투자를 원합니다. 어떤 상품을 추천하시나요?",
    "cot1": "먼저 고객의 현재 상황과 투자 목적을 파악해보겠습니다.",
    "cot2": "고객의 위험성향과 투자 기간을 고려하여 적합한 상품군을 선별합니다.",
    "cot3": "선별된 상품들의 특징과 장단점을 비교 분석합니다.",
    "answer": "고객의 상황에 맞는 최적의 상품을 추천드립니다.",
    "status": "검토중",
    "author": "관리자",
    "createdAt": "2025-08-25T11:23:29.974Z",
    "updatedAt": "2025-09-20T22:49:15.359Z"
  },
  {
    "id": "cot-017",
    "productSource": "증권",
    "questionType": "상품비교 추천형",
    "questioner": "user-0049",
    "products": [
      "product-045"
    ],
    "question": "30대 직장인으로 안정적인 투자를 원합니다. 어떤 상품을 추천하시나요?",
    "cot1": "먼저 고객의 현재 상황과 투자 목적을 파악해보겠습니다.",
    "cot2": "고객의 위험성향과 투자 기간을 고려하여 적합한 상품군을 선별합니다.",
    "cot3": "선별된 상품들의 특징과 장단점을 비교 분석합니다.",
    "answer": "고객의 상황에 맞는 최적의 상품을 추천드립니다.",
    "status": "완료",
    "author": "관리자",
    "createdAt": "2025-09-18T19:32:26.356Z",
    "updatedAt": "2025-09-20T22:49:15.359Z"
  },
  {
    "id": "cot-018",
    "productSource": "보험",
    "questionType": "건강 및 질병 보장 대비형",
    "questioner": "user-0059",
    "products": [
      "product-019",
      "product-048"
    ],
    "question": "건강에 대한 걱정이 많아 실손보험을 알아보고 있습니다.",
    "cot1": "먼저 고객의 현재 상황과 투자 목적을 파악해보겠습니다.",
    "cot2": "고객의 위험성향과 투자 기간을 고려하여 적합한 상품군을 선별합니다.",
    "cot3": "선별된 상품들의 특징과 장단점을 비교 분석합니다.",
    "answer": "고객의 상황에 맞는 최적의 상품을 추천드립니다.",
    "status": "검토중",
    "author": "관리자",
    "createdAt": "2025-08-21T23:28:46.508Z",
    "updatedAt": "2025-09-20T22:49:15.359Z"
  },
  {
    "id": "cot-019",
    "productSource": "증권",
    "questionType": "고객 특성 강조형",
    "questioner": "user-0049",
    "products": [
      "product-013",
      "product-049",
      "product-026"
    ],
    "question": "은퇴 준비를 위한 장기 투자 상품을 찾고 있습니다.",
    "cot1": "먼저 고객의 현재 상황과 투자 목적을 파악해보겠습니다.",
    "cot2": "고객의 위험성향과 투자 기간을 고려하여 적합한 상품군을 선별합니다.",
    "cot3": "선별된 상품들의 특징과 장단점을 비교 분석합니다.",
    "answer": "고객의 상황에 맞는 최적의 상품을 추천드립니다.",
    "status": "보류",
    "author": "관리자",
    "createdAt": "2025-09-04T09:29:12.599Z",
    "updatedAt": "2025-09-20T22:49:15.359Z"
  },
  {
    "id": "cot-020",
    "productSource": "보험",
    "questionType": "건강 및 질병 보장 대비형",
    "questioner": "user-0082",
    "products": [
      "product-031",
      "product-030",
      "product-014"
    ],
    "question": "건강에 대한 걱정이 많아 실손보험을 알아보고 있습니다.",
    "cot1": "먼저 고객의 현재 상황과 투자 목적을 파악해보겠습니다.",
    "cot2": "고객의 위험성향과 투자 기간을 고려하여 적합한 상품군을 선별합니다.",
    "cot3": "선별된 상품들의 특징과 장단점을 비교 분석합니다.",
    "answer": "고객의 상황에 맞는 최적의 상품을 추천드립니다.",
    "status": "검토중",
    "author": "관리자",
    "createdAt": "2025-08-30T05:17:37.182Z",
    "updatedAt": "2025-09-20T22:49:15.359Z"
  },
  {
    "id": "cot-021",
    "productSource": "증권",
    "questionType": "고객 특성 강조형",
    "questioner": "user-0093",
    "products": [
      "product-016",
      "product-045",
      "product-026"
    ],
    "question": "해외 투자에 관심이 있는데 초보자도 할 수 있는 상품이 있나요?",
    "cot1": "먼저 고객의 현재 상황과 투자 목적을 파악해보겠습니다.",
    "cot2": "고객의 위험성향과 투자 기간을 고려하여 적합한 상품군을 선별합니다.",
    "cot3": "선별된 상품들의 특징과 장단점을 비교 분석합니다.",
    "answer": "고객의 상황에 맞는 최적의 상품을 추천드립니다.",
    "status": "초안",
    "author": "관리자",
    "createdAt": "2025-08-23T18:14:01.102Z",
    "updatedAt": "2025-09-20T22:49:15.359Z"
  },
  {
    "id": "cot-022",
    "productSource": "증권",
    "questionType": "투자성향 및 조건 기반형",
    "questioner": "user-0087",
    "products": [
      "product-015",
      "product-006"
    ],
    "question": "30대 직장인으로 안정적인 투자를 원합니다. 어떤 상품을 추천하시나요?",
    "cot1": "먼저 고객의 현재 상황과 투자 목적을 파악해보겠습니다.",
    "cot2": "고객의 위험성향과 투자 기간을 고려하여 적합한 상품군을 선별합니다.",
    "cot3": "선별된 상품들의 특징과 장단점을 비교 분석합니다.",
    "answer": "고객의 상황에 맞는 최적의 상품을 추천드립니다.",
    "status": "완료",
    "author": "관리자",
    "createdAt": "2025-09-12T23:52:22.172Z",
    "updatedAt": "2025-09-20T22:49:15.359Z"
  },
  {
    "id": "cot-023",
    "productSource": "보험",
    "questionType": "건강 및 질병 보장 대비형",
    "questioner": "user-0023",
    "products": [
      "product-016",
      "product-038",
      "product-033"
    ],
    "question": "건강에 대한 걱정이 많아 실손보험을 알아보고 있습니다.",
    "cot1": "먼저 고객의 현재 상황과 투자 목적을 파악해보겠습니다.",
    "cot2": "고객의 위험성향과 투자 기간을 고려하여 적합한 상품군을 선별합니다.",
    "cot3": "선별된 상품들의 특징과 장단점을 비교 분석합니다.",
    "answer": "고객의 상황에 맞는 최적의 상품을 추천드립니다.",
    "status": "완료",
    "author": "관리자",
    "createdAt": "2025-08-23T11:52:44.294Z",
    "updatedAt": "2025-09-20T22:49:15.359Z"
  },
  {
    "id": "cot-024",
    "productSource": "증권",
    "questionType": "고객 특성 강조형",
    "questioner": "user-0023",
    "products": [
      "product-049",
      "product-043"
    ],
    "question": "30대 직장인으로 안정적인 투자를 원합니다. 어떤 상품을 추천하시나요?",
    "cot1": "먼저 고객의 현재 상황과 투자 목적을 파악해보겠습니다.",
    "cot2": "고객의 위험성향과 투자 기간을 고려하여 적합한 상품군을 선별합니다.",
    "cot3": "선별된 상품들의 특징과 장단점을 비교 분석합니다.",
    "answer": "고객의 상황에 맞는 최적의 상품을 추천드립니다.",
    "status": "완료",
    "author": "관리자",
    "createdAt": "2025-08-31T11:05:54.711Z",
    "updatedAt": "2025-09-20T22:49:15.359Z"
  },
  {
    "id": "cot-025",
    "productSource": "증권",
    "questionType": "투자성향 및 조건 기반형",
    "questioner": "user-0093",
    "products": [
      "product-038",
      "product-030"
    ],
    "question": "30대 직장인으로 안정적인 투자를 원합니다. 어떤 상품을 추천하시나요?",
    "cot1": "먼저 고객의 현재 상황과 투자 목적을 파악해보겠습니다.",
    "cot2": "고객의 위험성향과 투자 기간을 고려하여 적합한 상품군을 선별합니다.",
    "cot3": "선별된 상품들의 특징과 장단점을 비교 분석합니다.",
    "answer": "고객의 상황에 맞는 최적의 상품을 추천드립니다.",
    "status": "검토중",
    "author": "관리자",
    "createdAt": "2025-09-17T17:25:17.490Z",
    "updatedAt": "2025-09-20T22:49:15.359Z"
  },
  {
    "id": "cot-026",
    "productSource": "보험",
    "questionType": "건강 및 질병 보장 대비형",
    "questioner": "user-0077",
    "products": [
      "product-032",
      "product-046"
    ],
    "question": "40대 가장으로서 가족을 위한 보장보험을 찾고 있습니다.",
    "cot1": "먼저 고객의 현재 상황과 투자 목적을 파악해보겠습니다.",
    "cot2": "고객의 위험성향과 투자 기간을 고려하여 적합한 상품군을 선별합니다.",
    "cot3": "선별된 상품들의 특징과 장단점을 비교 분석합니다.",
    "answer": "고객의 상황에 맞는 최적의 상품을 추천드립니다.",
    "status": "보류",
    "author": "관리자",
    "createdAt": "2025-09-18T02:33:14.847Z",
    "updatedAt": "2025-09-20T22:49:15.359Z"
  },
  {
    "id": "cot-027",
    "productSource": "증권",
    "questionType": "투자성향 및 조건 기반형",
    "questioner": "user-0003",
    "products": [
      "product-041",
      "product-028"
    ],
    "question": "해외 투자에 관심이 있는데 초보자도 할 수 있는 상품이 있나요?",
    "cot1": "먼저 고객의 현재 상황과 투자 목적을 파악해보겠습니다.",
    "cot2": "고객의 위험성향과 투자 기간을 고려하여 적합한 상품군을 선별합니다.",
    "cot3": "선별된 상품들의 특징과 장단점을 비교 분석합니다.",
    "answer": "고객의 상황에 맞는 최적의 상품을 추천드립니다.",
    "status": "검토중",
    "author": "관리자",
    "createdAt": "2025-08-25T08:54:24.146Z",
    "updatedAt": "2025-09-20T22:49:15.359Z"
  },
  {
    "id": "cot-028",
    "productSource": "증권",
    "questionType": "투자성향 및 조건 기반형",
    "questioner": "user-0050",
    "products": [
      "product-043"
    ],
    "question": "30대 직장인으로 안정적인 투자를 원합니다. 어떤 상품을 추천하시나요?",
    "cot1": "먼저 고객의 현재 상황과 투자 목적을 파악해보겠습니다.",
    "cot2": "고객의 위험성향과 투자 기간을 고려하여 적합한 상품군을 선별합니다.",
    "cot3": "선별된 상품들의 특징과 장단점을 비교 분석합니다.",
    "answer": "고객의 상황에 맞는 최적의 상품을 추천드립니다.",
    "status": "완료",
    "author": "관리자",
    "createdAt": "2025-08-27T08:17:10.324Z",
    "updatedAt": "2025-09-20T22:49:15.359Z"
  },
  {
    "id": "cot-029",
    "productSource": "보험",
    "questionType": "투자성 상품 추천형",
    "questioner": "user-0093",
    "products": [
      "product-028",
      "product-007",
      "product-005"
    ],
    "question": "노후 준비를 위한 연금보험 상품을 추천해주세요.",
    "cot1": "먼저 고객의 현재 상황과 투자 목적을 파악해보겠습니다.",
    "cot2": "고객의 위험성향과 투자 기간을 고려하여 적합한 상품군을 선별합니다.",
    "cot3": "선별된 상품들의 특징과 장단점을 비교 분석합니다.",
    "answer": "고객의 상황에 맞는 최적의 상품을 추천드립니다.",
    "status": "초안",
    "author": "관리자",
    "createdAt": "2025-08-24T13:22:01.800Z",
    "updatedAt": "2025-09-20T22:49:15.359Z"
  },
  {
    "id": "cot-030",
    "productSource": "증권",
    "questionType": "상품비교 추천형",
    "questioner": "user-0027",
    "products": [
      "product-003"
    ],
    "question": "은퇴 준비를 위한 장기 투자 상품을 찾고 있습니다.",
    "cot1": "먼저 고객의 현재 상황과 투자 목적을 파악해보겠습니다.",
    "cot2": "고객의 위험성향과 투자 기간을 고려하여 적합한 상품군을 선별합니다.",
    "cot3": "선별된 상품들의 특징과 장단점을 비교 분석합니다.",
    "answer": "고객의 상황에 맞는 최적의 상품을 추천드립니다.",
    "status": "초안",
    "author": "관리자",
    "createdAt": "2025-08-28T02:19:22.138Z",
    "updatedAt": "2025-09-20T22:49:15.359Z"
  }
]